docdoc/__init__.py
docdoc/matching.py
docdoc/postprocessing.py
docdoc/preprocessing.py
docdoc/tokenization.py
docdoc/resource/custom_english_non_breaking_prefixes.txt
docdoc/resource/stopwords.txt
docdoc-0.1.1.dist-info/LICENSE
docdoc-0.1.1.dist-info/METADATA
docdoc-0.1.1.dist-info/WHEEL
docdoc-0.1.1.dist-info/top_level.txt
docdoc-0.1.1.dist-info/RECORD
