Metadata-Version: 2.1
Name: docdoc
Version: 0.1.1
Summary: A tool to handle documents
Home-page: https://github.com/click-me/docdoc
Author: Enno
Author-email: hi.xiaolonghuang@gmail.com
License: UNKNOWN
Platform: UNKNOWN
Classifier: Programming Language :: Python :: 3
Classifier: License :: OSI Approved :: MIT License
Classifier: Operating System :: OS Independent
Requires-Python: >=3.7
Requires-Dist: sentence-splitter (>=1.4)
Requires-Dist: nltk (>=3.4.5)
Requires-Dist: numpy (>=1.18.3)
Requires-Dist: bert-for-tf2 (>=0.14.4)
Requires-Dist: spacy (>=2.2.4)
